clickup_api_client/__init__.py
clickup_api_client/client.py
clickup_api_client/exceptions.py
clickup_api_client/models.py
clickup_api_client/helpers/__init__.py
clickup_api_client/helpers/formatting.py
clickup_api_client/helpers/timefuncs.py
tests/__init__.py
tests/test_client.py
tests/tests_client.py
clickup_api_client-1.0.5.dist-info/METADATA
clickup_api_client-1.0.5.dist-info/WHEEL
clickup_api_client-1.0.5.dist-info/top_level.txt
clickup_api_client-1.0.5.dist-info/RECORD
