Metadata-Version: 2.4
Name: clickup-api-client
Version: 1.0.5
Summary: clickup-api-client: A Python client for the ClickUp API
Home-page: https://github.com/sgavka/clickup-sdk
Author: Gavka Serhiy
Author-email: sgavka@gmail.com
Project-URL: Bug Reports, https://github.com/sgavka/clickup-sdk/issues
Project-URL: Source Code, https://github.com/sgavka/clickup-sdk
Keywords: clickup,clickup api,python,clickup-api-client,sdk
Requires-Python: >=3.6
Requires-Dist: pydantic
Requires-Dist: typing-extensions
Requires-Dist: word2number
Requires-Dist: timefhuman
Requires-Dist: pendulum
Requires-Dist: typing-extensions
Requires-Dist: setuptools
Dynamic: author
Dynamic: author-email
Dynamic: description
Dynamic: description-content-type
Dynamic: home-page
Dynamic: keywords
Dynamic: project-url
Dynamic: requires-dist
Dynamic: requires-python
Dynamic: summary
